[
    {
        "URL1": "https://www.hamropatro.com/news",
        "URL2": "https://www.hamropatro.com/news/details/5648635757723648?ns=",
        "Title": "अष्ट्रेलियामा बिदा मनाउँदा नेपालीहरुले ध्यान दिनैपर्ने कुराहरु",
        "Summary": "सिड्नी । पछिल्लो समय अष्ट्रेलियामा नेपाली विद्यार्थीहरुको संख्या उल्लेख्य रहेको छ । तर, नयाँ ठाउँमा नयाँ अन्तरवस्तुबारे जानकारी नहुँदा विभिन्न दुर्घटना हुने गरेको छ । यतिबेला धेरैजना क्रिसमससहित नय...",
        "URL3": "http://www.nepalipatra.com/news/australia/37820"
    },
    {
        "URL1": "https://www.hamropatro.com/news",
        "URL2": "https://www.hamropatro.com/news/details/5695946701537280?ns=",
        "Title": "गुल्मीको वडा कार्यालयमा तोडफोड, केही रकम पनि लुटियाे",
        "Summary": "गुल्मी – गुल्मीको मालिका गाउँपालिका ७ को वडा कार्यालयमा मंगलबार राति तोडफोड गरिएको छ । नचिनेको मान्छेको समूहले मंगलबार राति वडाध्यक्षको कार्यकक्षसहित अन्य कोठाहरूमा समेत ताेडफोड गरेको वडाध्यक्ष वे...",
        "URL3": "https://ujyaaloonline.com/story/30395/2019/12/25/gulmi-based-malika-ward-office-breakage"
    },
    {
        "URL1": "https://www.hamropatro.com/news",
        "URL2": "https://www.hamropatro.com/news/details/6207229205020672?ns=",
        "Title": "नेपाली युवतीलाई भारतमा बलि चढाउने योजना ! सातजना पक्राउ",
        "Summary": "काठमाडौं । नेपाली युवतीलाई भारतीय एक धार्मिक गुरुको आश्रममा लगेर बलि दिने योजना प्रहरीले असफल पारेको दाबी गरेको छ ।  प्रहरी उच्च स्रोतले दिएको जानकारीअनुसार ती युवतीलाई भारतमा लगेर बलि दिने तयारी ग...",
        "URL3": "https://baahrakhari.com/feed-detail.php?nid=231859"
    },
    {
        "URL1": "https://www.hamropatro.com/news",
        "URL2": "https://www.hamropatro.com/news/details/5636615687766016?ns=",
        "Title": "भातृ संगठनलाई चाडै पूर्णता दिन्छौं, गम्भीर छलफल भइरहेको छ: बरिष्ठ नेता पौडेल",
        "Summary": "काठमाडौं । नेपाली कांग्रेसका बरिष्ठ नेता रामचन्द्र पौडेलले पार्टीले भातृसंगठनलाई चाडै पूर्णता दिने आश्वासन दिएका छन् । आज(बुधबार) आफ्नै निवास बोहोराटारमा नेपाल विद्यार्थीसंघका प्रतिनिधिसँगको भेटमा...",
        "URL3": "https://www.imagekhabar.com/news/25545/-"
    },
    {
        "URL1": "https://www.hamropatro.com/news",
        "URL2": "https://www.hamropatro.com/news/details/5132141915406336?ns=",
        "Title": "तेह्रौँ सागमा रजत र कास्य जितेका खेलाडीका लागि पुरस्कार घोषणा गर्न माग",
        "Summary": "काठमाडौँ । राष्ट्रिय तथा अन्तरराष्ट्रिय खेलाडी सङ्घले हालै नेपालमा सम्पन्न १३औँ दक्षिण एशियाली खेलकूद (साग) मा पदक जितेका खेलाडीलाई पुरस्कारको घोषणा गर्न सरकारसँग माग गरेको छ । सागमा टिम इभेन्टतर्फ...",
        "URL3": "https://rajdhanidaily.com/207474/"
    },
    {
        "URL1": "https://www.hamropatro.com/news",
        "URL2": "https://www.hamropatro.com/news/details/5084202664853504?ns=",
        "Title": "१७ अर्ब डलर बढ्यो मुकेश अम्बानीको सम्पत्ति",
        "Summary": "पुस ९, नयाँ दिल्ली (भारत) । भारतीय व्यापारी तथा एशियाका सर्वाधिक धनी व्यक्ति मुकेश अम्बानीको लागि यो वर्ष निकै राम्रो रह्यो । सन् २०१९ को डिसेम्बर २३ सम्मको अवधिमा उनको सम्पत्ति करीब १७ अर्ब डलरले...",
        "URL3": "https://www.abhiyandaily.com/newscategory-detail/363848"
    },
    {
        "URL1": "https://www.hamropatro.com/news",
        "URL2": "https://www.hamropatro.com/news/details/5719640968658944?ns=",
        "Title": "यूनियन मेवा हाइड्रोले साधारण सभा गर्दै",
        "Summary": "यूनियन मेवा हाइड्रो लिमिडेट कम्पनीले आफ्नो तेस्रो औँ वार्षिक साधारण सभा पौष २३ गते बोलाएको छ । कम्पनीले ऐन २०६३ को दफा ६७ अनुसार विभिन्न विषयमा सेयरधनीहरुलाई जानकारी गराउन उक्त सभा बोलाएको छ ।  स...",
        "URL3": "http://ajakoartha.com/story/23177"
    },
    {
        "URL1": "https://www.hamropatro.com/news",
        "URL2": "https://www.hamropatro.com/news/details/5096015972401152?ns=",
        "Title": "सलमानसँग काम गर्न तयार छुः अक्षय",
        "Summary": "केही समय अगाडिसम्म नायक साहरुख खान र सलमान खानका फ्यानको वार सामाजिक संजालमा खुबै देखिन्थ्यो । तर, अहिले साहरुख र सलमान सबैभन्दा मिल्ने साथी भएका छन् । यसपछि भने साहरुख र सलमानका फ्यानको मित्रता पन...",
        "URL3": "https://www.onlinekhabar.com/2019/12/823059"
    },
    {
        "URL1": "https://www.hamropatro.com/news",
        "URL2": "https://www.hamropatro.com/news/details/5671466736418816?ns=",
        "Title": "मौसमको मार : तराईमा हुस्सु लाग्दा काठमाडौंको आन्तरिक विमानस्थलमा ‘मानव मेला’",
        "Summary": "कृष्ण पाण्डे काठमाडौं , ९ पुष । शीतलहर र बाक्लो हुस्सुका कारण मध्य र पश्चिम तराईका जिल्लाहरुको मौसममा सुधार नआउँदा त्यस्को असर हवाई उडानमा परेको छ । हुस्सुले तराईका जिल्लाका विमानस्थलहरुको भिजिबि...",
        "URL3": "https://www.news24nepal.tv/2019/12/25/605406"
    },
    {
        "URL1": "https://www.hamropatro.com/news",
        "URL2": "https://www.hamropatro.com/news/details/5761097127559168?ns=",
        "Title": "दाङमा बीस हजार सवारी चालक कारवाहीमा",
        "Summary": "चालू आर्थिक वर्षको पहिलो पाँच महिनामा दाङमा २० हजार तीन सय सवारी चालक कारवाहीमा परेका छन् ।  जिल्ला ट्राफिक प्रहरी कार्यालय दाङका प्रमुख प्रेमप्रसाद रेग्मीका अनुसार, ट्राफिक नियम विपरित सवारी चलाउ...",
        "URL3": "http://ajakoartha.com/story/23178"
    },
    {
        "URL1": "https://www.hamropatro.com/news",
        "URL2": "https://www.hamropatro.com/news/details/5747492080451584?ns=",
        "Title": "काजक्रिया छाडेर ‘श्रद्धाञ्जली सभा’",
        "Summary": "ओखलढुंगा : नेकपाका आमन्त्रित स्थायी समिति सदस्य पेशल खतिवडा बुवाको काजक्रिया गर्न कपाल काटेर कोरामा बसेनन्। उनी मंसिर २९ गते बुवाको निधन भएपछि अन्तिम संस्कारमा सहभागी भए। फर्केर घरमा बुवाको फोटोमा ...",
        "URL3": "http://annapurnapost.com/news/143908"
    },
    {
        "URL1": "https://www.hamropatro.com/news",
        "URL2": "https://www.hamropatro.com/news/details/5167343400255488?ns=",
        "Title": "भाजपा किन कमजोर बनिरहेको छ ?",
        "Summary": "आउँदो हप्ता सन् २०१९ विदा हुँदैछ । विश्वभरी यो वर्षलाई सम्झिने कारण फरक/फरक हुनेछन् । भारतको सत्तारुढ पार्टी भारतीय जनता पार्टी (भाजपा) का लागि भने यो वर्ष उन्नतिको पराकाष्ठा र ओरालो यात्राको वर्ष ...",
        "URL3": "https://www.sajhapost.com/2019/12/25/209294.html"
    },
    {
        "URL1": "https://www.hamropatro.com/news",
        "URL2": "https://www.hamropatro.com/news/details/5653557259665408?ns=",
        "Title": "यस्ता स्वभाव भएका व्यक्ती जाे जीवनमा कहिल्यै धनी बन्नै सक्दैनन्",
        "Summary": "पुस ९ । धनी बन्ने रहर सबै मानिसको हुन्छ । तर अक्सर मान्छेले गरिबी मै आफ्नो जीवन व्यतित गर्छ । मानिस गरिबी हुनुमा विभिन्न कारण हुन्छ र कमजोरीहरु हुन्छन् । आज हामी त्यही कारण र कमजोरीहरु उल्लेख गर्न ...",
        "URL3": "https://makalukhabar.com/news/250990"
    },
    {
        "URL1": "https://www.hamropatro.com/news",
        "URL2": "https://www.hamropatro.com/news/details/5695156159119360?ns=",
        "Title": "11 parties granted symbols for NA election",
        "Summary": "The Election Commission (EC) has granted different election symbols to those political parties taking part in the upcoming National Assembly election scheduled for next month. A total of 11 politi...",
        "URL3": "https://www.lokpath.com/story/209541"
    },
    {
        "URL1": "https://www.hamropatro.com/news",
        "URL2": "https://www.hamropatro.com/news/details/5158732057935872?ns=",
        "Title": "३० करोड आइफोन ह्याक गरी एप्पलसँग फिरौती मागेपछि….",
        "Summary": "२२ वर्षीय एक ह्याकरलाई अमेरिकी कम्पनी एप्पलसँग फिरौती मागेर ब्लाकमेल गर्नु निकै महँगो सावित भएको छ । ती ह्याकरले ३० करोड आइफोन ह्याक गरी आइक्लाउड अकाउन्टका डाटा हात पारेका थिए । त्यसपछि उनले ती आइ...",
        "URL3": "https://www.onlinekhabar.com/2019/12/823061"
    },
    {
        "URL1": "https://www.hamropatro.com/news",
        "URL2": "https://www.hamropatro.com/news/details/5648200086978560?ns=",
        "Title": "रोनाल्डो र मेस्सीभन्दा बढी कमाउने खेलाडी बक्सर मेवेदर",
        "Summary": "अमेरिकी बक्सर फ्लोयड मेवेदर दशक यताकै सर्वाधिक कमाउने खेलाडी बनेका छन्। फुटबलका स्टार क्रिस्टियानो रोनाल्डो र लियोनल मेस्सीलाई उछिन्दै मेवेदर सर्वाधिक कमाउने खेलाडी बनेका हुन्। फोर्ब्सले हालै जार...",
        "URL3": "https://nepalkhabar.com/sports/15321-2019-12-25-06-21-00"
    },
    {
        "URL1": "https://www.hamropatro.com/news",
        "URL2": "https://www.hamropatro.com/news/details/5672261573804032?ns=",
        "Title": "'छपाक' लाई कथा चोरीको आरोप",
        "Summary": "एजेन्सीः बलिउड स्टार दीपिका पादुकोण हाल 'छपाक' को प्रचार-प्रसारमा व्यस्त छिन् । फिल्म जनवरी १०, २०२० मा रिलिज हुने तयारीमा छ । तर रिलिज हुनुअघि नै फिल्म कानुनी विवादमा तानिएको छ। फिल्म छपाकविरुद्ध...",
        "URL3": "http://annapurnapost.com/news/143909"
    },
    {
        "URL1": "https://www.hamropatro.com/news",
        "URL2": "https://www.hamropatro.com/news/details/5718772043087872?ns=",
        "Title": "Bahrain tourism minister expresses keen interest to visit Nepal",
        "Summary": "Kathmandu–Nepal's Ambassador to Bahrain, Padma Sundas has extended an invitation to Bahrain's Minister for Industry, Commerce and Tourism Zayad Bin Rashid Al Zayani for Nepal visit. Ambassador Sun...",
        "URL3": "http://english.ratopati.com/story/11402"
    },
    {
        "URL1": "https://www.hamropatro.com/news",
        "URL2": "https://www.hamropatro.com/news/details/5637006261354496?ns=",
        "Title": "अज्ञात समूहद्वारा वडा कार्यालय तोडफोड",
        "Summary": "बुटवल । गुल्मीको मालिका गाउँपालिका वडा नम्बर ७ को वडा कार्यालय अज्ञात समूहले तोडफोड गरेको छ ।  घमिरमा रहेको वडा कार्यालय तोडफोड भएको त्यस गाउँपालिकाका प्रमुख प्रशासकीय अधिकृत दीपक भण्डारीले जानकार...",
        "URL3": "https://ratopati.com/story/111147/2019/12/25/todfod"
    },
    {
        "URL1": "https://www.hamropatro.com/news",
        "URL2": "https://www.hamropatro.com/news/details/5724753584062464?ns=",
        "Title": "पेस्तोल बोकेर हिँड्ने सेनाका भगौडा प्रहरीको फन्दामा",
        "Summary": "काठमाडौँ । महानगरीय अपराध महाशाखाको टोलीले एक व्यक्तिलाई पक्राउ गरेको छ । काठमाडौँ महानगरपालिकास्थित बालुवाखानीतिर हतियार बोकेर हिँडिरहेको भन्ने सूचनाको आधारमा महाशाखाको विशेष टोलीले रामेछाप मन्थल...",
        "URL3": "https://ratopati.com/story/111151/2019/12/25/pestol"
    },
    {
        "URL1": "https://www.hamropatro.com/news",
        "URL2": "https://www.hamropatro.com/news/details/5741132173410304?ns=",
        "Title": "स्वास्थ्यका लागि आयुर्वेद र जीवनशैली",
        "Summary": "स्वस्थ्य भन्नाले निरोगिताको अवस्था र वृत्त भन्नाले व्यक्तिले अबलम्वन गर्ने बानी–व्यवहार बुझिन्छ। आयर्वेदमा स्वस्थ व्यक्तिको स्वास्थ्यको सुरक्षालाई पहिलो प्राथमिकता र रोगीको उपचारलाई त्यसपछिको उपायक...",
        "URL3": "https://swasthyakhabar.com/story/30138"
    },
    {
        "URL1": "https://www.hamropatro.com/news",
        "URL2": "https://www.hamropatro.com/news/details/5768466620350464?ns=",
        "Title": "मीरगञ्ज पुल बन्द, भीमनगरको बाटो प्रयोगका लागि पहल गरिदिन माग",
        "Summary": "९ पुस, विराटनगर । नेपालको दोस्रो ठूला नाका विराटनगरमा मीरगञ्ज पुलका कारण उद्योग र व्यापारमा समस्या आएको छ । भारतबाट जोगबनी आउन मीरगञ्ज पुल पार गर्नुपर्छ । पूर्व क्षेत्रको उद्योग र व्यापारलाई आवश्यक...",
        "URL3": "https://www.onlinekhabar.com/2019/12/823057"
    },
    {
        "URL1": "https://www.hamropatro.com/news",
        "URL2": "https://www.hamropatro.com/news/details/5134624406503424?ns=",
        "Title": "सुटिङमै कलाकारको गेटअप सार्वजनिक, फस्टलुकलाई के राख्ने ?",
        "Summary": "चलचित्र ‘सेल्फी किङ्ग’को पोष्टर सार्वजनिक हुँदा यसले राम्रो चर्चा पायो । चलचित्रको पोष्टरमा देखिएको नायक विपिन कार्कीको लुक्स त्यसअघि सार्वजनिक भएको थिएन । निर्माणपक्षले पनि, विपिनको लुक्सलाई लुकाउ...",
        "URL3": "https://www.onlinekhabar.com/2019/12/823054"
    },
    {
        "URL1": "https://www.hamropatro.com/news",
        "URL2": "https://www.hamropatro.com/news/details/5656688961912832?ns=",
        "Title": "सेलपे सेवा र सस्ताेडिलबीच सहकार्य",
        "Summary": "काठमाडाैं- सेलपे सेवा र सस्ताेडिलबीच सहकार्य सेल ए ब्रासन अफरका लागि सहकार्य भएकाे छ। नेपाल राष्ट्र बैंकबाट अनुमति प्राप्त भुक्तानी सेवा प्रदायक सेलकम प्रा. लि. को सेलपे सेवाले नेपालको शीर्ष ई- कमर...",
        "URL3": "https://nepallive.com/story/197781"
    },
    {
        "URL1": "https://www.hamropatro.com/news",
        "URL2": "https://www.hamropatro.com/news/details/5741495366582272?ns=",
        "Title": "जाडोमा नछोड्नुस् व्यायाम, लाग्ला यस्ता रोग",
        "Summary": "काठमाडौं– चिसोको समयमा कतिपय मानिसहरु अल्छि हुन्छन् । दैनिक गर्नुपर्ने शारीरिक व्यायाम तथा योगा गर्दैनन् । जसले गर्दा शरीरि सक्रिया हुन सक्दैन । चिसो मौसममा मर्डिङ वाक लगायतका कार्य गर्दा बढी चिसो ...",
        "URL3": "https://www.khabarhub.com/2019/25/115047/"
    },
    {
        "URL1": "https://www.hamropatro.com/news",
        "URL2": "https://www.hamropatro.com/news/details/5668446562811904?ns=",
        "Title": "एनआरएनए पदाधिकारीद्वारा श्रममन्त्रीसँग भेट",
        "Summary": "गैरआवासीय नेपाली संघका उपाध्यक्ष तथा वैदेशिक रोजगार विभागका सभापति डा. बद्री केसी लगायतका पदाधिकारीहरुले नवनियुक्त श्रम रोजगार तथा सामाजिक सुरक्षा मन्त्री रामेश्वरराय यादवसँग भेटघाट गरेको छ । भेटक...",
        "URL3": "https://www.karobardaily.com/news/migration/27158"
    },
    {
        "URL1": "https://www.hamropatro.com/news",
        "URL2": "https://www.hamropatro.com/news/details/5651806114676736?ns=",
        "Title": "प्रचण्डका खेल सारथी",
        "Summary": "ललितपुर । ललितपुर पुल्चोकका रैथाने सुदिल शाही टेबलटेनिस (टिटी) का अब्बल खेलाडी हुन् । तर सुदिलको परिचय खेलाडीमा मात्र सिमित छैन । ३५ वर्षदेखि खेल क्षेत्रमा सक्रिय सुदिलको पछिल्लो परिचय नेपाली राजनि...",
        "URL3": "https://ratopati.com/story/111146/2019/12/25/sudil-sahi-prachanda-table-tennis-"
    },
    {
        "URL1": "https://www.hamropatro.com/news",
        "URL2": "https://www.hamropatro.com/news/details/5726363592818688?ns=",
        "Title": "दुनियाँकै खतरनाक ठाउँ जहाँ भइसकेको छ ५०० परमाणु बमको परीक्षण",
        "Summary": "कजाखस्तानको दी पोलिगनको इतिहास आफैंमा खतरनाक छ । सन् १९४९ देखि १९८९ को बीचमा हरेक वर्ष त्यहाँ १० वटा परमाणु बमको परीक्षण गरिएको थियो । त्यसको नतिजा आजसम्म पनि त्यहाँ देख्न पाइन्छ । शीतयुद्धको बेला...",
        "URL3": "https://www.onlinekhabar.com/2019/12/823058"
    },
    {
        "URL1": "https://www.hamropatro.com/news",
        "URL2": "https://www.hamropatro.com/news/details/5177031443480576?ns=",
        "Title": "टेस्लाले सांघाईमा फ्याक्ट्री बनाउन चिनियाँ बैंकसँग लियो १.४ अर्ब डलर ऋण",
        "Summary": "काठमाडौं- अमेरिकी इलेक्ट्रिक कार उत्पादक कम्पनी टेस्लाले चीनमा समेत आफ्नो उत्पादन प्लान्ट बनाउँदै छ। त्यसका लागि टेस्लाले चिनियाँ बैंकहरुसँग १ अर्ब ४० करोड अमेरिकी डलर (१० अर्ब युआन) लिएको छ। टेस्...",
        "URL3": "https://nepallive.com/story/197801"
    },
    {
        "URL1": "https://www.hamropatro.com/news",
        "URL2": "https://www.hamropatro.com/news/details/5722098824511488?ns=",
        "Title": "सप्तरीमा जीप र मोटरसाइकल ठोक्किँदा २ जनाको मृत्यु",
        "Summary": "सप्तरी । तिब्र गतिमा गुडिरहेको जीप र मोटरसाइकल एक आपसमा ठोक्किँदा दुई जनाको ज्यान गएको छ । पूर्वपश्चिम राजमार्ग अन्तरगत सप्तरीको रुपनी गाउँपालिका खण्डमा पर्ने बिरेन्द्र बजार नजिकै मंगलबार राति १० ...",
        "URL3": "https://rajdhanidaily.com/207468/"
    },
    {
        "URL1": "https://www.hamropatro.com/news",
        "URL2": "https://www.hamropatro.com/news/details/5718571112857600?ns=",
        "Title": "सुन ६ सयले बढ्यो, कति पुग्यो तोलाको ?",
        "Summary": "काठमाडौं : नेपाली बजारमा सुन-चाँदीको मूल्य बढ्ने क्रम जारी छ।बुधबार सुन तोलामा ६ सयले बढेर ७२ हजार ८ सय रुपैयाँमा कारोबार भइरहेको नेपाल सुन चाँदी व्यवसाय महासंघले जनाएको छ।तेजावीको सुनको मूल्य पनि ...",
        "URL3": "http://annapurnapost.com/news/143907"
    },
    {
        "URL1": "https://www.hamropatro.com/news",
        "URL2": "https://www.hamropatro.com/news/details/5650286971322368?ns=",
        "Title": "गैरआवासीय नेपालीको छवि सुधार्ने महासचिवको प्रतिबद्धता",
        "Summary": "गैरआवासीय नेपाली संघ (एनआरएनए) का महासचिव डा. हेमराज शर्माले आफ्नो दुई वर्षे कार्यकालमा कुनै परिवर्तन नआए अर्को पटक नेतृत्वको चुनावी मैदानमा आफू नहुने प्रतिबद्धता व्यक्त गरेका छन् । उनले गैरआवासीय ...",
        "URL3": "https://www.karobardaily.com/news/migration/27156"
    },
    {
        "URL1": "https://www.hamropatro.com/news",
        "URL2": "https://www.hamropatro.com/news/details/5708576321306624?ns=",
        "Title": "Visit Year to begin with cultural procession",
        "Summary": "Gandaki State government and tourism entrepreneurs here have stepped up their internal preparations to make Visit Nepal Year-2020 a success. In order to allure both domestic and foreign tourists, ...",
        "URL3": "https://canadanepal.com/content/6323"
    },
    {
        "URL1": "https://www.hamropatro.com/news",
        "URL2": "https://www.hamropatro.com/news/details/5701261192986624?ns=",
        "Title": "‘ज्योति फिल्मस म्युजिक एवार्ड’ फागुनमा",
        "Summary": "काठमाडौं । ज्योति फिल्मस् प्रोडक्सनले गीत र कलाकारको प्रोत्साहनका लागि आगामी फागुन १ गते ‘ज्योति फिल्मस म्युजिक एवार्ड’ कार्यक्रम गर्न लागेको छ  । विसं २०७५ वैशाख १ देखि पुस २० गतेसम्म बजारमा आएका ...",
        "URL3": "https://rajdhanidaily.com/207475/"
    },
    {
        "URL1": "https://www.hamropatro.com/news",
        "URL2": "https://www.hamropatro.com/news/details/5694384681910272?ns=",
        "Title": "११ हजार युवालाई तालिम",
        "Summary": "काठमाडौं : सरकारले झन्डै ११ बेरोजगार युवालाई सीपमूलक तालिम दिने भएको छ। तालिमपछि रोजगारीमा जान सक्ने, आफैं व्यवसाय सञ्चालन गर्न सक्षम बन्ने व्यावसायिक शिक्षा तथा तालिम अभिवृद्धि परियोजना (इभेन्ट)ले...",
        "URL3": "http://annapurnapost.com/news/143905"
    },
    {
        "URL1": "https://www.hamropatro.com/news",
        "URL2": "https://www.hamropatro.com/news/details/5708166420365312?ns=",
        "Title": "दंग सुरक्षा !",
        "Summary": "काठमाडौं । सुरक्षा पन्त मेथड एक्टर बन्ने दौडमा छिन् । मेथड एक्टिङको बाटो हिँड्न सुरु गरेका सौगात मल्ल, दयाहाङ राई आदिले चाँडै लत्तो छाडेपछि सुरक्षा यो बाटो हिँड्ने तरखरमा छिन् । यसको झल्को दिइसकेक...",
        "URL3": "http://www.nepalipatra.com/news/suraksha-panta-/37819"
    },
    {
        "URL1": "https://www.hamropatro.com/news",
        "URL2": "https://www.hamropatro.com/news/details/5717388124094464?ns=",
        "Title": "बालाजु बाइपास–बाइसधारा सडक सात वर्षसम्म नबनेको भन्दै विरोधमा स्थानीय",
        "Summary": "काठमाडौं । ‘सडक निर्माणमा ढिलाइ भएको’ भन्दै बालाजु बाइपासका स्थानीय विरोधमा उत्रिएका छन्  । काठमाडौं–१६ बाइपास–बाइसधारासम्मको लगभग ३ सय मिटर सडक सात वर्षसम्म पनि निर्माण सम्पन्न नभएको भन्दै उनीहरू ...",
        "URL3": "https://rajdhanidaily.com/207480/"
    },
    {
        "URL1": "https://www.hamropatro.com/news",
        "URL2": "https://www.hamropatro.com/news/details/5175473773346816?ns=",
        "Title": "दाता बनेर लाखौं रुपैयाँ ठगी",
        "Summary": "दोलखा : दोलखाको पश्चिमी शैलुङ गाउँपालिकाको विद्यालयमा शैक्षिक सामग्री सहयोग गर्ने भन्दै गत भदौमा भारतको सिक्किमबाट शैलुङ पसेका सिक्किम विकलांग सेवा समाज, सिक्किम भारतका अध्यक्ष दिपक गौतमले दाता बने...",
        "URL3": "http://annapurnapost.com/news/143906"
    },
    {
        "URL1": "https://www.hamropatro.com/news",
        "URL2": "https://www.hamropatro.com/news/details/5652983076225024?ns=",
        "Title": "Visit Year 2020 to begin with cultural procession in Pokhara",
        "Summary": "Image for Representation POKHARA: The Gandaki State government and tourism entrepreneurs have intensified internal preparations to make Visit Nepal 2020 a success. In a bid to allure domestic and...",
        "URL3": "https://english.khabarhub.com/2019/25/64290/"
    }
]